dataloader_fetcher/__init__.py
dataloader_fetcher-0.0.1.dist-info/LICENSE
dataloader_fetcher-0.0.1.dist-info/WHEEL
dataloader_fetcher-0.0.1.dist-info/METADATA
dataloader_fetcher-0.0.1.dist-info/RECORD
